scalesim/__init__.py
scalesim/layout_utils.py
scalesim/scale.py
scalesim/scale_config.py
scalesim/scale_sim.py
scalesim/simulator.py
scalesim/single_layer_sim.py
scalesim/topology_utils.py
scalesim/compute/__init__.py
scalesim/compute/compression.py
scalesim/compute/operand_matrix.py
scalesim/compute/systolic_compute_is.py
scalesim/compute/systolic_compute_os.py
scalesim/compute/systolic_compute_ws.py
scalesim/memory/__init__.py
scalesim/memory/double_buffered_scratchpad_mem.py
scalesim/memory/read_buffer.py
scalesim/memory/read_buffer_estimate_bw.py
scalesim/memory/read_buffer_old.py
scalesim/memory/read_port.py
scalesim/memory/write_buffer.py
scalesim/memory/write_buffer_old.py
scalesim/memory/write_port.py
scalesim/utilities/__init__.py
scalesim/utilities/scalesim_report.py
scalesim-3.0.0.dist-info/LICENSE
scalesim-3.0.0.dist-info/METADATA
scalesim-3.0.0.dist-info/WHEEL
scalesim-3.0.0.dist-info/top_level.txt
scalesim-3.0.0.dist-info/RECORD
