Metadata-Version: 2.1
Name: scalesim
Version: 3.0.0
Summary: Systolic CNN AcceLerator Simulator
Home-page: https://github.com/scalesim-project/SCALE-Sim
Author: ritikraj7, anands09, tushar
Author-email: ritik.raj@gatech.edu
Maintainer: SynergyLab, GT
Maintainer-email: ritik.raj@gatech.edu
License: MIT
Classifier: Development Status :: 3 - Alpha
Classifier: Intended Audience :: Developers
Classifier: Intended Audience :: Education
Classifier: Intended Audience :: Science/Research
Classifier: License :: OSI Approved :: MIT License
Classifier: Operating System :: OS Independent
Classifier: Programming Language :: Python :: 3
Classifier: Programming Language :: Python :: 3.7
Classifier: Programming Language :: Python :: Implementation :: PyPy
Classifier: Topic :: Scientific/Engineering
License-File: LICENSE
Requires-Dist: numpy
Requires-Dist: configparser
Requires-Dist: absl-py
Requires-Dist: tqdm
Requires-Dist: pandas
Requires-Dist: setuptools
Requires-Dist: matplotlib
Requires-Dist: cython
Requires-Dist: numba
